<?xml version="1.0" encoding="UTF-8" ?>
<XMLDB PATH="mod/teamsmeeting/db" VERSION="20200704" COMMENT="XMLDB file for Moodle mod_teamsmeeting"
    xmlns:xsi="http://www.w3.org/2001/XMLSchema-instance"
    xsi:noNamespaceSchemaLocation="../../../lib/xmldb/xmldb.xsd"
>
  <TABLES>
    <TABLE NAME="teamsmeeting" COMMENT="Stores the teamsmeeting activity module instances.">
      <FIELDS>
        <FIELD NAME="id" TYPE="int" LENGTH="10" NOTNULL="true" SEQUENCE="true"/>
        <FIELD NAME="course" TYPE="int" LENGTH="10" NOTNULL="true" SEQUENCE="false" COMMENT="ID of the course this activity is part of."/>
        <FIELD NAME="name" TYPE="char" LENGTH="255" NOTNULL="true" SEQUENCE="false" COMMENT="The name of the activity module instance"/>
        <FIELD NAME="intro" TYPE="text" NOTNULL="false" SEQUENCE="false" COMMENT="Activity description."/>
        <FIELD NAME="introformat" TYPE="int" LENGTH="4" NOTNULL="true" DEFAULT="0" SEQUENCE="false" COMMENT="The format of the intro field."/>
        <FIELD NAME="openingtime" TYPE="int" LENGTH="10" NOTNULL="true" DEFAULT="0" SEQUENCE="false"/>
        <FIELD NAME="closingtime" TYPE="int" LENGTH="10" NOTNULL="true" DEFAULT="0" SEQUENCE="false"/>
        <FIELD NAME="membership" TYPE="int" LENGTH="4" NOTNULL="true" DEFAULT="0" SEQUENCE="false"/>
        <FIELD NAME="allowedpresenters" TYPE="CHAR" LENGTH="30" NOTNULL="true" DEFAULT="" SEQUENCE="false"/>
        <FIELD NAME="lobbybypass" TYPE="CHAR" LENGTH="30" NOTNULL="true" DEFAULT="" SEQUENCE="false"/>
        <FIELD NAME="joinannounce" TYPE="int" LENGTH="4" NOTNULL="true" DEFAULT="0" SEQUENCE="false"/>        
        <FIELD NAME="authtype" TYPE="char" LENGTH="255" NOTNULL="false" SEQUENCE="false"/>
        <FIELD NAME="showrecordings" TYPE="int" LENGTH="1" NOTNULL="true" DEFAULT="0" SEQUENCE="false"/>
        <FIELD NAME="wait" TYPE="int" LENGTH="1" NOTNULL="true" DEFAULT="0" SEQUENCE="false"/>
        <FIELD NAME="useafterwards" TYPE="int" LENGTH="1" NOTNULL="true" DEFAULT="0" SEQUENCE="false"/>
        <FIELD NAME="externalurl" TYPE="text" NOTNULL="false" SEQUENCE="false"/>
        <FIELD NAME="notifytime" TYPE="int" LENGTH="10" NOTNULL="true" DEFAULT="0" SEQUENCE="false"/>
        <FIELD NAME="timecreated" TYPE="int" LENGTH="10" NOTNULL="true" DEFAULT="0" SEQUENCE="false" COMMENT="Timestamp of when the instance was added to the course."/>
        <FIELD NAME="timemodified" TYPE="int" LENGTH="10" NOTNULL="true" DEFAULT="0" SEQUENCE="false" COMMENT="Timestamp of when the instance was last modified."/>
      </FIELDS>
      <KEYS>
        <KEY NAME="primary" TYPE="primary" FIELDS="id"/>
        <KEY NAME="course" TYPE="foreign" FIELDS="course" REFTABLE="course" REFFIELDS="id"/>
      </KEYS>
    </TABLE>
    <TABLE NAME="teamsmeeting_overrides" COMMENT="Stores the teamsmeeting o365 object information.">
      <FIELDS>
        <FIELD NAME="id" TYPE="int" LENGTH="10" NOTNULL="true" SEQUENCE="true"/>
        <FIELD NAME="teamsmeetingid" TYPE="int" LENGTH="10" NOTNULL="true" SEQUENCE="false"/>
        <FIELD NAME="groupid" TYPE="int" LENGTH="10" NOTNULL="true" SEQUENCE="false"/>
        <FIELD NAME="openingtime" TYPE="int" LENGTH="10" NOTNULL="true" DEFAULT="0" SEQUENCE="false"/>
        <FIELD NAME="closingtime" TYPE="int" LENGTH="10" NOTNULL="true" DEFAULT="0" SEQUENCE="false"/>
        <FIELD NAME="notifytime" TYPE="int" LENGTH="10" NOTNULL="true"  DEFAULT="0" SEQUENCE="false"/>
        <FIELD NAME="timemodified" TYPE="int" LENGTH="10" NOTNULL="true" DEFAULT="0" SEQUENCE="false" COMMENT="Timestamp of when the instance was last modified."/>
      </FIELDS>
      <KEYS>
        <KEY NAME="primary" TYPE="primary" FIELDS="id"/>
        <KEY NAME="teamsmeeting" TYPE="foreign" FIELDS="teamsmeetingid" REFTABLE="teamsmeeting" REFFIELDS="id"/>
        <KEY NAME="group" TYPE="foreign" FIELDS="groupid" REFTABLE="groups" REFFIELDS="id"/>
      </KEYS>
    </TABLE>
    <TABLE NAME="teamsmeeting_onlinemeeting" COMMENT="Stores the teamsmeeting o365 object information.">
      <FIELDS>
        <FIELD NAME="id" TYPE="int" LENGTH="10" NOTNULL="true" SEQUENCE="true"/>
        <FIELD NAME="teamsmeetingid" TYPE="int" LENGTH="10" NOTNULL="true" SEQUENCE="false"/>
        <FIELD NAME="groupid" TYPE="int" LENGTH="10" NOTNULL="true" SEQUENCE="false"/>
        <FIELD NAME="teacherid" TYPE="int" LENGTH="10" NOTNULL="true" SEQUENCE="false"/>
        <FIELD NAME="timeactivated" TYPE="int" LENGTH="10" NOTNULL="true" DEFAULT="0" SEQUENCE="false"/>        
        <FIELD NAME="meetingid" TYPE="char" LENGTH="255" NOTNULL="false" SEQUENCE="false"/>
        <FIELD NAME="externalid" TYPE="char" LENGTH="255" NOTNULL="false" SEQUENCE="false"/>
        <FIELD NAME="vtcid" TYPE="char" LENGTH="255" NOTNULL="false" SEQUENCE="false"/>
        <FIELD NAME="joinurl" TYPE="text" NOTNULL="false" SEQUENCE="false"/>
        <FIELD NAME="chatinfotid" TYPE="char" LENGTH="255" NOTNULL="false" SEQUENCE="false"/>
        <FIELD NAME="status" TYPE="int" LENGTH="4" NOTNULL="true" DEFAULT="0" SEQUENCE="false"/>
        <FIELD NAME="endtime" TYPE="int" LENGTH="10" NOTNULL="true" DEFAULT="0" SEQUENCE="false"/>        
        <FIELD NAME="expired" TYPE="int" LENGTH="1" NOTNULL="true" DEFAULT="0" SEQUENCE="false"/>
        <FIELD NAME="timecreated" TYPE="int" LENGTH="10" NOTNULL="true" DEFAULT="0" SEQUENCE="false" COMMENT="Timestamp of when the instance was added to the course."/>
        <FIELD NAME="timemodified" TYPE="int" LENGTH="10" NOTNULL="true" DEFAULT="0" SEQUENCE="false" COMMENT="Timestamp of when the instance was last modified."/>
      </FIELDS>
      <KEYS>
        <KEY NAME="primary" TYPE="primary" FIELDS="id"/>
        <KEY NAME="teamsmeeting" TYPE="foreign" FIELDS="teamsmeetingid" REFTABLE="teamsmeeting" REFFIELDS="id"/>
        <KEY NAME="group" TYPE="foreign" FIELDS="groupid" REFTABLE="groups" REFFIELDS="id"/>
      </KEYS>
    </TABLE>
    <TABLE NAME="teamsmeeting_recording" COMMENT="Stores the teamsmeeting recordings.">
      <FIELDS>
        <FIELD NAME="id" TYPE="int" LENGTH="10" NOTNULL="true" SEQUENCE="true"/>
        <FIELD NAME="onlinemeetingid" TYPE="int" LENGTH="10" NOTNULL="true" SEQUENCE="false"/>
        <FIELD NAME="name" TYPE="char" LENGTH="255" NOTNULL="false" SEQUENCE="false"/>
        <FIELD NAME="description" TYPE="text" NOTNULL="false" SEQUENCE="false" COMMENT="Activity description."/>
        <FIELD NAME="descriptionformat" TYPE="int" LENGTH="4" NOTNULL="true" DEFAULT="0" SEQUENCE="false" COMMENT="The format of the drecription field."/>
        <FIELD NAME="streamurl" TYPE="text" NOTNULL="false" SEQUENCE="false"/>
        <FIELD NAME="visible" TYPE="int" LENGTH="1" NOTNULL="true" DEFAULT="0" SEQUENCE="false"/>
        <FIELD NAME="timecreated" TYPE="int" LENGTH="10" NOTNULL="true" DEFAULT="0" SEQUENCE="false" COMMENT="Timestamp of when the instance was added to the course."/>
        <FIELD NAME="timemodified" TYPE="int" LENGTH="10" NOTNULL="true" DEFAULT="0" SEQUENCE="false" COMMENT="Timestamp of when the instance was last modified."/>
      </FIELDS>
      <KEYS>
        <KEY NAME="primary" TYPE="primary" FIELDS="id"/>
        <KEY NAME="meetingid" TYPE="foreign" FIELDS="onlinemeetingid" REFTABLE="teamsmeeting_onlinemeeting" REFFIELDS="id"/>
      </KEYS>
    </TABLE>
  </TABLES>
</XMLDB>
